[
    {
        "id": "1",
        "img": "project1.jpg",
        "title": "Projet 1",
        "description": "Ceci est une courte description du projet",
        "url": "https://google.com/"
    },
    {
        "id": "2",
        "img": "project1.jpg",
        "title": "La folie des grandeurs ! Voici mon super projet.",
        "description": "Voici la description de mon super projet, clique pour le découvrir !",
        "url": "https://google.com/"
    },
    {
        "id": "3",
        "img": "project1.jpg",
        "title": "Projet 3",
        "description": "Ceci est une courte description du projet",
        "url": "https://google.com/"
    },
    {
        "id": "4",
        "img": "project1.jpg",
        "title": "Projet 4",
        "description": "Ceci est une courte description du projet",
        "url": "https://google.com/"
    },
    {
        "id": "5",
        "img": "project1.jpg",
        "title": "Projet 5",
        "description": "Ceci est une courte description du projet",
        "url": "https://google.com/"
    }
]